data/__init__.py
data/curve.py
weltetools/__init__.py
weltetools/data.py
weltetools-0.0.1.dist-info/METADATA
weltetools-0.0.1.dist-info/WHEEL
weltetools-0.0.1.dist-info/top_level.txt
weltetools-0.0.1.dist-info/RECORD
